portfolio_backtest/__init__.py
portfolio_backtest/portfolio_backtest.py
portfolio_backtest-0.3.0.dist-info/METADATA
portfolio_backtest-0.3.0.dist-info/WHEEL
portfolio_backtest-0.3.0.dist-info/top_level.txt
portfolio_backtest-0.3.0.dist-info/RECORD
