Metadata-Version: 2.1
Name: portfolio-backtest
Version: 0.3.0
Summary: portfolio-backtest is a python library         for backtest portfolio asset allocation on Python 3.7 and above.
Home-page: https://github.com/10mohi6/portfolio-backtest-python
Author: 10mohi6
Author-email: 10.mohi.6.y@gmail.com
License: MIT
Keywords: portfolio stock ETF mutual fund python backtest         asset allocation CVaR HRP Variance Minimum tangency
Platform: UNKNOWN
Classifier: Development Status :: 4 - Beta
Classifier: Programming Language :: Python
Classifier: Programming Language :: Python :: 3
Classifier: Programming Language :: Python :: 3.7
Classifier: Programming Language :: Python :: 3.8
Classifier: Programming Language :: Python :: 3.9
Classifier: Intended Audience :: Developers
Classifier: Intended Audience :: Financial and Insurance Industry
Classifier: Operating System :: OS Independent
Classifier: Topic :: Office/Business :: Financial :: Investment
Classifier: License :: OSI Approved :: MIT License
Requires-Python: >=3.7.0
Requires-Dist: pandas
Requires-Dist: yfinance
Requires-Dist: matplotlib
Requires-Dist: scikit-learn
